examples/config.yaml
kgenealogic/__init__.py
kgenealogic/__main__.py
kgenealogic/cli.py
kgenealogic/cluster.py
kgenealogic/data.py
kgenealogic/files.py
kgenealogic/genetmap.csv
kgenealogic/schema.py
kgenealogic-0.2.3.dist-info/LICENSE
kgenealogic-0.2.3.dist-info/METADATA
kgenealogic-0.2.3.dist-info/WHEEL
kgenealogic-0.2.3.dist-info/RECORD
