Metadata-Version: 2.1
Name: kgenealogic
Version: 0.2.3
Summary: Genetic genealogy tool for tree structure inference
License: MIT
Author: John Wilmes
Author-email: jw@johnwilmes.name
Requires-Python: >=3.8,<3.12
Classifier: License :: OSI Approved :: MIT License
Classifier: Programming Language :: Python :: 3
Classifier: Programming Language :: Python :: 3.8
Classifier: Programming Language :: Python :: 3.9
Classifier: Programming Language :: Python :: 3.10
Classifier: Programming Language :: Python :: 3.11
Requires-Dist: numpy (>=1.24.3,<2.0.0)
Requires-Dist: pandas (>=2.0.1,<3.0.0)
Requires-Dist: pyyaml (>=6.0.1,<7.0.0)
Requires-Dist: scipy (>=1.10.1,<2.0.0)
Requires-Dist: sqlalchemy (>=2.0.15,<3.0.0)
Requires-Dist: typer (>=0.9.0,<0.10.0)
